automationshield/__init__.py
automationshield/arduino/aeroshield/aeroshield.ino
automationshield/arduino/floatshield/floatshield.ino
automationshield/arduino/lib/aeroshield/aeroshield.cpp
automationshield/arduino/lib/aeroshield/aeroshield.h
automationshield/arduino/lib/automationshield/automationshield.cpp
automationshield/arduino/lib/automationshield/automationshield.h
automationshield/arduino/lib/floatshield/floatshield.cpp
automationshield/arduino/lib/floatshield/floatshield.h
automationshield/arduino/lib/magnetoshield/magnetoshield.cpp
automationshield/arduino/lib/magnetoshield/magnetoshield.h
automationshield/arduino/magnetoshield/magnetoshield.ino
automationshield/arduino/out/arduino.avr.leonardo_aeroshield.ino.hex
automationshield/arduino/out/arduino.avr.leonardo_floatshield.ino.hex
automationshield/arduino/out/arduino.avr.leonardo_magnetoshield.ino.hex
automationshield/arduino/out/arduino.avr.mega_aeroshield.ino.hex
automationshield/arduino/out/arduino.avr.mega_floatshield.ino.hex
automationshield/arduino/out/arduino.avr.mega_magnetoshield.ino.hex
automationshield/arduino/out/arduino.avr.uno_aeroshield.ino.hex
automationshield/arduino/out/arduino.avr.uno_floatshield.ino.hex
automationshield/arduino/out/arduino.avr.uno_magnetoshield.ino.hex
automationshield/arduino.py
automationshield/controller/__init__.py
automationshield/controller/controller.py
automationshield/controller/reference.py
automationshield/exception.py
automationshield/plotting/__init__.py
automationshield/plotting/live_plotter.py
automationshield/plotting/plotter.py
automationshield/shields/__init__.py
automationshield/shields/aeroshield.py
automationshield/shields/baseshield.py
automationshield/shields/floatshield.py
automationshield/shields/magnetoshield.py
automationshield/shields/statespaceshield.py
python_automationshield-1.2.1.dist-info/METADATA
python_automationshield-1.2.1.dist-info/WHEEL
python_automationshield-1.2.1.dist-info/licenses/LICENSE
python_automationshield-1.2.1.dist-info/RECORD
