Metadata-Version: 2.4
Name: python-automationshield
Version: 1.2.1
Summary: A Python interface to AutomationShield's Arduino shields
License: MIT
License-File: LICENSE
Author: Bert Van den Abbeele
Requires-Python: >=3.10
Classifier: License :: OSI Approved :: MIT License
Classifier: Programming Language :: Python :: 3
Classifier: Programming Language :: Python :: 3.10
Classifier: Programming Language :: Python :: 3.11
Classifier: Programming Language :: Python :: 3.12
Classifier: Programming Language :: Python :: 3.13
Classifier: Programming Language :: Python :: 3.14
Provides-Extra: scipy
Requires-Dist: matplotlib (>=3.8.2)
Requires-Dist: multiprocess (>=0.70.16)
Requires-Dist: numpy (>=1.26.3)
Requires-Dist: pyserial (>=3.5)
Requires-Dist: scipy (>=1.14.1) ; extra == "scipy"
Project-URL: Documentation, https://python-automationshield.readthedocs.io
Project-URL: Repository, https://gitlab.com/mrtreasurer/python-automationshield
